Metadata-Version: 2.1
Name: minecraft-data
Version: 3.20.0
Summary: Provide easy access to minecraft data in python
Home-page: https://github.com/SpockBotMC/python-minecraft-data
Maintainer: Vito Gamberini
Maintainer-email: vito@gamberini.email
License: MIT
Keywords: minecraft
Classifier: License :: OSI Approved :: MIT License
License-File: LICENSE
